Metadata-Version: 1.1
Name: structured-data-seo
Version: 1.0.0
Summary: Structured Data SEO is a package for grow your site ranking using LD JSON
Home-page: https://github.com/pypa/sampleproject
Author: Fabricio Magalhães Sena
Author-email: fabricioms.dev@gmail.com
License: UNKNOWN
Keywords: SEO,LD+Json,metadata,Structured Data
Platform: UNKNOWN
Classifier: Development Status :: 3 - Alpha
Classifier: Intended Audience :: Developers
Classifier: Topic :: Software Development :: Build Tools
Classifier: License :: OSI Approved :: MIT License
Classifier: Programming Language :: Python :: 3
Classifier: Programming Language :: Python :: 3.4
Classifier: Programming Language :: Python :: 3.5
Classifier: Programming Language :: Python :: 3.6
